jsonmodel/__init__.py
jsonmodel/_extensions.py
jsonmodel/exceptions.py
jsonmodel/extensions.py
jsonmodel/loader.py
jsonmodel/mapping.py
jsonmodel/validators.py
jsonmodel/models/model-rules.json
jsonmodel-3.4.dist-info/LICENSE.txt
jsonmodel-3.4.dist-info/METADATA
jsonmodel-3.4.dist-info/WHEEL
jsonmodel-3.4.dist-info/top_level.txt
jsonmodel-3.4.dist-info/RECORD
