Metadata-Version: 2.1
Name: jsonmodel
Version: 3.4
Summary: A Collection of Methods for Validating JSON Structured Data
Home-page: https://github.com/collectiveacuity/jsonModel
Author: rcj1492
Author-email: support@collectiveacuity.com
Maintainer-email: support@collectiveacuity.com
License: MIT
Platform: UNKNOWN
Classifier: Development Status :: 4 - Beta
Classifier: Environment :: Web Environment
Classifier: Intended Audience :: Developers
Classifier: License :: OSI Approved :: MIT License
Classifier: Natural Language :: English
Classifier: Programming Language :: Python
Classifier: Programming Language :: Python :: 3.5
